netwrix-api/__init__.py
netwrix_api/__init__.py
netwrix_api-0.0.7.dist-info/METADATA
netwrix_api-0.0.7.dist-info/RECORD
netwrix_api-0.0.7.dist-info/WHEEL
netwrix_api-0.0.7.dist-info/top_level.txt
