Metadata-Version: 2.1
Name: netwrix-api
Version: 0.0.7
Summary: A library to interact with Netwrix Search API
Home-page: https://github.com/BongoEADGC6/netwrix-api
Author: Cliff Hults
Author-email: bongoeadgc6@gmail.com
License: UNKNOWN
Platform: UNKNOWN
Classifier: Programming Language :: Python :: 3
Classifier: License :: OSI Approved :: MIT License
Classifier: Operating System :: OS Independent
Requires-Dist: requests
